{"is_source_file": false, "format": "", "description": "", "external_files": [], "external_methods": [], "published": [], "classes": [], "methods": [], "calls": [], "search-terms": [], "state": 2, "file_id": 21, "knowledge_revision": 37, "git_revision": "136174297a166c50b4d78d562e35e5d77cf274a0", "hash": "f83be5f2c7897cc8dde86132053c0702", "format-version": 4, "code-base-name": "tic_tac_toe_frontend", "filename": "README.md", "revision_history": [{"37": "136174297a166c50b4d78d562e35e5d77cf274a0"}]}